django_auto_translator/__init__.py
django_auto_translator/compat.py
django_auto_translator/models.py
django_auto_translator/services.py
django_auto_translator/utils.py
django_auto_translator/management/__init__.py
django_auto_translator/management/commands/__init__.py
django_auto_translator/management/commands/translate_messages.py
django_auto_translator/tests/__init__.py
django_auto_translator-0.1.2.dist-info/METADATA
django_auto_translator-0.1.2.dist-info/WHEEL
django_auto_translator-0.1.2.dist-info/licenses/LICENSE
django_auto_translator-0.1.2.dist-info/RECORD
