Metadata-Version: 2.3
Name: django_auto_translator
Version: 0.1.2
Summary: Automatically translate Django's pot Files
Project-URL: Homepage, https://github.com/myridia/django_auto_translator
Project-URL: Issues, https://github.com/myridia/django_auto_translator/issues
Author-email: Myridia <django_auto_translator@myridia.com>
License-File: LICENSE
Classifier: License :: OSI Approved :: GNU General Public License v3 or later (GPLv3+)
Classifier: Operating System :: OS Independent
Classifier: Programming Language :: Python :: 3
Requires-Python: >=3.8
